yuisub/__init__.py
yuisub/__main__.py
yuisub/a2t.py
yuisub/bangumi.py
yuisub/llm.py
yuisub/prompt.py
yuisub/sub.py
yuisub/translator.py
yuisub-1.3.0.dist-info/LICENSE
yuisub-1.3.0.dist-info/METADATA
yuisub-1.3.0.dist-info/WHEEL
yuisub-1.3.0.dist-info/entry_points.txt
yuisub-1.3.0.dist-info/RECORD
